{
  "name": "v83empire", // ปรับให้ตรงกับโปรเจกต์หลัก
  "main": "src/index.ts",
  "compatibility_date": "2026-05-06",
  "compatibility_flags": [ "nodejs_compat" ], // เพิ่มความสามารถในการประมวลผล Layer
  "kv_namespaces": [
    { 
      "binding": "TNH_KV", 
      "id": "2fa0a4773efa4a18b1534274d238dd76" 
    }
  ],
  "d1_databases": [
    { 
      "binding": "DB", 
      "database_id": "6a8b4373-bf40-4b63-bb02-f612ecbe63b7" // แก้ไข ID ให้ตรงกับฐานข้อมูลจริง
    }
  ],
  "r2_buckets": [
    { 
      "binding": "TNH_R2", 
      "bucket_name": "thitnueahub-assets" 
    }
  ],
  "triggers": {
    "crons": ["0 0 */3 * *"] // ทำงานอัตโนมัติทุก 3 วันตามสถาปัตยกรรม V1
  }
}
